amazon_short_url/__init__.py
amazon_short_url/cli.py
amazon_short_url/test_cli.py
amazon_short_url-0.1.0.dist-info/METADATA
amazon_short_url-0.1.0.dist-info/WHEEL
amazon_short_url-0.1.0.dist-info/entry_points.txt
amazon_short_url-0.1.0.dist-info/RECORD
