Metadata-Version: 2.1
Name: amazon-short-url
Version: 0.1.0
Summary: A script to shorten Amazon Product page URLs.
Home-page: https://github.com/gh640/amazon-short-url
Author: Goto Hayato
Author-email: gh640@hey.com
Requires-Python: >=3.11,<4.0
Classifier: Environment :: Console
Classifier: License :: OSI Approved :: MIT License
Classifier: Programming Language :: Python :: 3
Classifier: Programming Language :: Python :: 3.11
Classifier: Programming Language :: Python :: 3 :: Only
Classifier: Topic :: Utilities
Requires-Dist: click (>=8.1.7,<9.0.0)
Project-URL: Repository, https://github.com/gh640/amazon-short-url
